{
  "date": "20260624",
  "periods": {
    "daily": {
      "sectors": [
        {
          "name": "基建投资",
          "count": 7,
          "keywords": {
            "交通运输": 1,
            "桥梁": 1,
            "基础设施": 1,
            "基建": 1,
            "铁路": 1
          }
        },
        {
          "name": "农业",
          "count": 4,
          "keywords": {
            "粮食": 1,
            "农产品": 1,
            "农业": 1
          }
        },
        {
          "name": "AI人工智能",
          "count": 3,
          "keywords": {
            "人工智能": 1
          }
        },
        {
          "name": "外贸",
          "count": 3,
          "keywords": {
            "一带一路": 1,
            "贸易": 1,
            "出口": 1
          }
        },
        {
          "name": "新能源",
          "count": 1,
          "keywords": {
            "新能源": 1
          }
        },
        {
          "name": "消费",
          "count": 1,
          "keywords": {
            "电商": 1
          }
        },
        {
          "name": "石油能源",
          "count": 1,
          "keywords": {
            "霍尔木兹": 1
          }
        },
        {
          "name": "军工",
          "count": 1,
          "keywords": {
            "导弹": 1
          }
        },
        {
          "name": "医药",
          "count": 1,
          "keywords": {
            "医疗": 1
          }
        }
      ],
      "top_keywords": [
        [
          "市场",
          5
        ],
        [
          "增长",
          4
        ],
        [
          "投资",
          3
        ],
        [
          "补贴",
          2
        ],
        [
          "财政",
          2
        ],
        [
          "预算",
          2
        ],
        [
          "产能",
          1
        ],
        [
          "贸易",
          1
        ],
        [
          "融资",
          1
        ],
        [
          "百分点",
          1
        ],
        [
          "同比",
          1
        ],
        [
          "亿元",
          1
        ],
        [
          "万亿",
          1
        ]
      ]
    },
    "weekly": {
      "sectors": [
        {
          "name": "基建投资",
          "count": 31,
          "keywords": {
            "铁路": 6,
            "交通运输": 5,
            "基础设施": 4,
            "港口": 3,
            "公路": 3,
            "桥梁": 2,
            "基建": 2
          }
        },
        {
          "name": "外贸",
          "count": 16,
          "keywords": {
            "出口": 4,
            "一带一路": 3,
            "贸易": 3,
            "进口": 3,
            "外贸": 1,
            "关税": 1
          }
        },
        {
          "name": "农业",
          "count": 12,
          "keywords": {
            "农业": 5,
            "粮食": 2,
            "农产品": 1,
            "种子": 1
          }
        },
        {
          "name": "石油能源",
          "count": 12,
          "keywords": {
            "霍尔木兹": 5,
            "天然气": 2,
            "原油": 2,
            "石油": 2,
            "油价": 1
          }
        },
        {
          "name": "AI人工智能",
          "count": 11,
          "keywords": {
            "人工智能": 4,
            "智能制造": 1,
            "算力": 1,
            "AI": 1,
            "智能体": 1
          }
        },
        {
          "name": "新能源",
          "count": 11,
          "keywords": {
            "新能源": 5,
            "光伏": 2,
            "核电": 1,
            "清洁能源": 1,
            "风电": 1
          }
        },
        {
          "name": "消费",
          "count": 11,
          "keywords": {
            "消费": 4,
            "电商": 2,
            "零售": 1,
            "商贸": 1
          }
        },
        {
          "name": "军工",
          "count": 9,
          "keywords": {
            "国防": 5,
            "导弹": 1,
            "航母": 1,
            "军工": 1
          }
        },
        {
          "name": "医药",
          "count": 6,
          "keywords": {
            "医疗": 2,
            "医药": 2,
            "生物医药": 1,
            "中药": 1
          }
        },
        {
          "name": "机器人",
          "count": 5,
          "keywords": {
            "机器人": 2,
            "人形机器人": 1
          }
        },
        {
          "name": "半导体",
          "count": 4,
          "keywords": {
            "半导体": 2,
            "集成电路": 1,
            "芯片": 1
          }
        },
        {
          "name": "房地产",
          "count": 4,
          "keywords": {
            "住房": 2,
            "城市更新": 1,
            "老旧小区": 1
          }
        },
        {
          "name": "新能源汽车",
          "count": 4,
          "keywords": {
            "新能源汽车": 2,
            "锂电池": 1
          }
        },
        {
          "name": "银行金融",
          "count": 3,
          "keywords": {
            "银行": 1,
            "利率": 1
          }
        },
        {
          "name": "黄金",
          "count": 2,
          "keywords": {
            "黄金": 2
          }
        },
        {
          "name": "煤炭",
          "count": 2,
          "keywords": {
            "煤炭": 1,
            "煤矿": 1
          }
        },
        {
          "name": "钢铁",
          "count": 1,
          "keywords": {
            "钢铁": 1
          }
        },
        {
          "name": "地下管网",
          "count": 1,
          "keywords": {
            "地下管网": 1
          }
        }
      ],
      "top_keywords": [
        [
          "增长",
          20
        ],
        [
          "市场",
          20
        ],
        [
          "投资",
          11
        ],
        [
          "同比",
          11
        ],
        [
          "亿元",
          8
        ],
        [
          "财政",
          7
        ],
        [
          "消费",
          7
        ],
        [
          "补贴",
          4
        ],
        [
          "贸易",
          4
        ],
        [
          "百分点",
          4
        ],
        [
          "预算",
          3
        ],
        [
          "产能",
          2
        ],
        [
          "万亿",
          2
        ],
        [
          "进出口",
          2
        ],
        [
          "万元",
          2
        ],
        [
          "产值",
          2
        ],
        [
          "融资",
          1
        ],
        [
          "通胀",
          1
        ],
        [
          "利润",
          1
        ],
        [
          "税收",
          1
        ],
        [
          "零售",
          1
        ],
        [
          "订单",
          1
        ],
        [
          "外贸",
          1
        ],
        [
          "千亿",
          1
        ],
        [
          "CPI",
          1
        ],
        [
          "关税",
          1
        ]
      ]
    },
    "monthly": {
      "sectors": [
        {
          "name": "基建投资",
          "count": 53,
          "keywords": {
            "铁路": 12,
            "交通运输": 7,
            "基础设施": 7,
            "港口": 6,
            "公路": 5,
            "基建": 3,
            "桥梁": 2,
            "机场": 1
          }
        },
        {
          "name": "农业",
          "count": 34,
          "keywords": {
            "农业": 12,
            "粮食": 7,
            "农产品": 2,
            "种子": 2,
            "夏收": 2,
            "耕地": 1
          }
        },
        {
          "name": "外贸",
          "count": 31,
          "keywords": {
            "贸易": 7,
            "出口": 7,
            "一带一路": 5,
            "外贸": 4,
            "进口": 3,
            "关税": 1
          }
        },
        {
          "name": "石油能源",
          "count": 30,
          "keywords": {
            "霍尔木兹": 11,
            "原油": 6,
            "油价": 5,
            "石油": 4,
            "天然气": 2,
            "炼化": 1
          }
        },
        {
          "name": "AI人工智能",
          "count": 29,
          "keywords": {
            "人工智能": 10,
            "AI": 6,
            "算力": 3,
            "智能体": 2,
            "大模型": 2,
            "智能制造": 1
          }
        },
        {
          "name": "消费",
          "count": 27,
          "keywords": {
            "消费": 10,
            "电商": 3,
            "零售": 2,
            "商贸": 2,
            "市场主体": 1
          }
        },
        {
          "name": "新能源",
          "count": 24,
          "keywords": {
            "新能源": 9,
            "光伏": 4,
            "清洁能源": 3,
            "风电": 3,
            "核电": 2
          }
        },
        {
          "name": "军工",
          "count": 19,
          "keywords": {
            "国防": 7,
            "导弹": 5,
            "战斗机": 2,
            "航母": 1,
            "军工": 1
          }
        },
        {
          "name": "银行金融",
          "count": 19,
          "keywords": {
            "银行": 5,
            "利率": 3,
            "贷款": 3,
            "央行": 2,
            "货币政策": 2
          }
        },
        {
          "name": "房地产",
          "count": 13,
          "keywords": {
            "住房": 5,
            "城市更新": 4,
            "老旧小区": 3,
            "房地产": 1
          }
        },
        {
          "name": "机器人",
          "count": 10,
          "keywords": {
            "机器人": 4,
            "人形机器人": 2,
            "具身智能": 1
          }
        },
        {
          "name": "医药",
          "count": 7,
          "keywords": {
            "医疗": 3,
            "医药": 2,
            "生物医药": 1,
            "中药": 1
          }
        },
        {
          "name": "数据要素",
          "count": 7,
          "keywords": {
            "数字经济": 4,
            "数据产品": 1,
            "数据局": 1
          }
        },
        {
          "name": "地下管网",
          "count": 6,
          "keywords": {
            "地下管网": 3,
            "管网改造": 1,
            "排水管道": 1,
            "综合管廊": 1
          }
        },
        {
          "name": "新能源汽车",
          "count": 6,
          "keywords": {
            "新能源汽车": 3,
            "锂电池": 2
          }
        },
        {
          "name": "半导体",
          "count": 5,
          "keywords": {
            "半导体": 3,
            "集成电路": 1,
            "芯片": 1
          }
        },
        {
          "name": "黄金",
          "count": 4,
          "keywords": {
            "黄金": 3,
            "金价": 1
          }
        },
        {
          "name": "煤炭",
          "count": 3,
          "keywords": {
            "煤炭": 1,
            "煤矿": 1,
            "煤电": 1
          }
        },
        {
          "name": "工程机械",
          "count": 3,
          "keywords": {
            "工程机械": 1,
            "挖掘机": 1,
            "装载机": 1
          }
        },
        {
          "name": "钢铁",
          "count": 2,
          "keywords": {
            "钢铁": 2
          }
        }
      ],
      "top_keywords": [
        [
          "市场",
          38
        ],
        [
          "增长",
          33
        ],
        [
          "投资",
          23
        ],
        [
          "亿元",
          22
        ],
        [
          "同比",
          21
        ],
        [
          "消费",
          19
        ],
        [
          "财政",
          13
        ],
        [
          "贸易",
          11
        ],
        [
          "万亿",
          9
        ],
        [
          "补贴",
          7
        ],
        [
          "预算",
          6
        ],
        [
          "万元",
          6
        ],
        [
          "百分点",
          5
        ],
        [
          "融资",
          4
        ],
        [
          "进出口",
          4
        ],
        [
          "外贸",
          4
        ],
        [
          "产值",
          4
        ],
        [
          "产能",
          3
        ],
        [
          "通胀",
          2
        ],
        [
          "税收",
          2
        ],
        [
          "零售",
          2
        ],
        [
          "订单",
          2
        ],
        [
          "千亿",
          2
        ],
        [
          "CPI",
          2
        ],
        [
          "国债",
          2
        ],
        [
          "GDP",
          2
        ],
        [
          "利润",
          1
        ],
        [
          "关税",
          1
        ],
        [
          "产量",
          1
        ],
        [
          "回升",
          1
        ]
      ]
    },
    "half_year": {
      "sectors": [
        {
          "name": "基建投资",
          "count": 53,
          "keywords": {
            "铁路": 12,
            "交通运输": 7,
            "基础设施": 7,
            "港口": 6,
            "公路": 5,
            "基建": 3,
            "桥梁": 2,
            "机场": 1
          }
        },
        {
          "name": "农业",
          "count": 34,
          "keywords": {
            "农业": 12,
            "粮食": 7,
            "农产品": 2,
            "种子": 2,
            "夏收": 2,
            "耕地": 1
          }
        },
        {
          "name": "外贸",
          "count": 31,
          "keywords": {
            "贸易": 7,
            "出口": 7,
            "一带一路": 5,
            "外贸": 4,
            "进口": 3,
            "关税": 1
          }
        },
        {
          "name": "石油能源",
          "count": 30,
          "keywords": {
            "霍尔木兹": 11,
            "原油": 6,
            "油价": 5,
            "石油": 4,
            "天然气": 2,
            "炼化": 1
          }
        },
        {
          "name": "AI人工智能",
          "count": 29,
          "keywords": {
            "人工智能": 10,
            "AI": 6,
            "算力": 3,
            "智能体": 2,
            "大模型": 2,
            "智能制造": 1
          }
        },
        {
          "name": "消费",
          "count": 27,
          "keywords": {
            "消费": 10,
            "电商": 3,
            "零售": 2,
            "商贸": 2,
            "市场主体": 1
          }
        },
        {
          "name": "新能源",
          "count": 24,
          "keywords": {
            "新能源": 9,
            "光伏": 4,
            "清洁能源": 3,
            "风电": 3,
            "核电": 2
          }
        },
        {
          "name": "军工",
          "count": 19,
          "keywords": {
            "国防": 7,
            "导弹": 5,
            "战斗机": 2,
            "航母": 1,
            "军工": 1
          }
        },
        {
          "name": "银行金融",
          "count": 19,
          "keywords": {
            "银行": 5,
            "利率": 3,
            "贷款": 3,
            "央行": 2,
            "货币政策": 2
          }
        },
        {
          "name": "房地产",
          "count": 13,
          "keywords": {
            "住房": 5,
            "城市更新": 4,
            "老旧小区": 3,
            "房地产": 1
          }
        },
        {
          "name": "机器人",
          "count": 10,
          "keywords": {
            "机器人": 4,
            "人形机器人": 2,
            "具身智能": 1
          }
        },
        {
          "name": "医药",
          "count": 7,
          "keywords": {
            "医疗": 3,
            "医药": 2,
            "生物医药": 1,
            "中药": 1
          }
        },
        {
          "name": "数据要素",
          "count": 7,
          "keywords": {
            "数字经济": 4,
            "数据产品": 1,
            "数据局": 1
          }
        },
        {
          "name": "地下管网",
          "count": 6,
          "keywords": {
            "地下管网": 3,
            "管网改造": 1,
            "排水管道": 1,
            "综合管廊": 1
          }
        },
        {
          "name": "新能源汽车",
          "count": 6,
          "keywords": {
            "新能源汽车": 3,
            "锂电池": 2
          }
        },
        {
          "name": "半导体",
          "count": 5,
          "keywords": {
            "半导体": 3,
            "集成电路": 1,
            "芯片": 1
          }
        },
        {
          "name": "黄金",
          "count": 4,
          "keywords": {
            "黄金": 3,
            "金价": 1
          }
        },
        {
          "name": "煤炭",
          "count": 3,
          "keywords": {
            "煤炭": 1,
            "煤矿": 1,
            "煤电": 1
          }
        },
        {
          "name": "工程机械",
          "count": 3,
          "keywords": {
            "工程机械": 1,
            "挖掘机": 1,
            "装载机": 1
          }
        },
        {
          "name": "钢铁",
          "count": 2,
          "keywords": {
            "钢铁": 2
          }
        }
      ],
      "top_keywords": [
        [
          "市场",
          38
        ],
        [
          "增长",
          33
        ],
        [
          "投资",
          23
        ],
        [
          "亿元",
          22
        ],
        [
          "同比",
          21
        ],
        [
          "消费",
          19
        ],
        [
          "财政",
          13
        ],
        [
          "贸易",
          11
        ],
        [
          "万亿",
          9
        ],
        [
          "补贴",
          7
        ],
        [
          "预算",
          6
        ],
        [
          "万元",
          6
        ],
        [
          "百分点",
          5
        ],
        [
          "融资",
          4
        ],
        [
          "进出口",
          4
        ],
        [
          "外贸",
          4
        ],
        [
          "产值",
          4
        ],
        [
          "产能",
          3
        ],
        [
          "通胀",
          2
        ],
        [
          "税收",
          2
        ],
        [
          "零售",
          2
        ],
        [
          "订单",
          2
        ],
        [
          "千亿",
          2
        ],
        [
          "CPI",
          2
        ],
        [
          "国债",
          2
        ],
        [
          "GDP",
          2
        ],
        [
          "利润",
          1
        ],
        [
          "关税",
          1
        ],
        [
          "产量",
          1
        ],
        [
          "回升",
          1
        ]
      ]
    },
    "yearly": {
      "sectors": [
        {
          "name": "基建投资",
          "count": 53,
          "keywords": {
            "铁路": 12,
            "交通运输": 7,
            "基础设施": 7,
            "港口": 6,
            "公路": 5,
            "基建": 3,
            "桥梁": 2,
            "机场": 1
          }
        },
        {
          "name": "农业",
          "count": 34,
          "keywords": {
            "农业": 12,
            "粮食": 7,
            "农产品": 2,
            "种子": 2,
            "夏收": 2,
            "耕地": 1
          }
        },
        {
          "name": "外贸",
          "count": 31,
          "keywords": {
            "贸易": 7,
            "出口": 7,
            "一带一路": 5,
            "外贸": 4,
            "进口": 3,
            "关税": 1
          }
        },
        {
          "name": "石油能源",
          "count": 30,
          "keywords": {
            "霍尔木兹": 11,
            "原油": 6,
            "油价": 5,
            "石油": 4,
            "天然气": 2,
            "炼化": 1
          }
        },
        {
          "name": "AI人工智能",
          "count": 29,
          "keywords": {
            "人工智能": 10,
            "AI": 6,
            "算力": 3,
            "智能体": 2,
            "大模型": 2,
            "智能制造": 1
          }
        },
        {
          "name": "消费",
          "count": 27,
          "keywords": {
            "消费": 10,
            "电商": 3,
            "零售": 2,
            "商贸": 2,
            "市场主体": 1
          }
        },
        {
          "name": "新能源",
          "count": 24,
          "keywords": {
            "新能源": 9,
            "光伏": 4,
            "清洁能源": 3,
            "风电": 3,
            "核电": 2
          }
        },
        {
          "name": "军工",
          "count": 19,
          "keywords": {
            "国防": 7,
            "导弹": 5,
            "战斗机": 2,
            "航母": 1,
            "军工": 1
          }
        },
        {
          "name": "银行金融",
          "count": 19,
          "keywords": {
            "银行": 5,
            "利率": 3,
            "贷款": 3,
            "央行": 2,
            "货币政策": 2
          }
        },
        {
          "name": "房地产",
          "count": 13,
          "keywords": {
            "住房": 5,
            "城市更新": 4,
            "老旧小区": 3,
            "房地产": 1
          }
        },
        {
          "name": "机器人",
          "count": 10,
          "keywords": {
            "机器人": 4,
            "人形机器人": 2,
            "具身智能": 1
          }
        },
        {
          "name": "医药",
          "count": 7,
          "keywords": {
            "医疗": 3,
            "医药": 2,
            "生物医药": 1,
            "中药": 1
          }
        },
        {
          "name": "数据要素",
          "count": 7,
          "keywords": {
            "数字经济": 4,
            "数据产品": 1,
            "数据局": 1
          }
        },
        {
          "name": "地下管网",
          "count": 6,
          "keywords": {
            "地下管网": 3,
            "管网改造": 1,
            "排水管道": 1,
            "综合管廊": 1
          }
        },
        {
          "name": "新能源汽车",
          "count": 6,
          "keywords": {
            "新能源汽车": 3,
            "锂电池": 2
          }
        },
        {
          "name": "半导体",
          "count": 5,
          "keywords": {
            "半导体": 3,
            "集成电路": 1,
            "芯片": 1
          }
        },
        {
          "name": "黄金",
          "count": 4,
          "keywords": {
            "黄金": 3,
            "金价": 1
          }
        },
        {
          "name": "煤炭",
          "count": 3,
          "keywords": {
            "煤炭": 1,
            "煤矿": 1,
            "煤电": 1
          }
        },
        {
          "name": "工程机械",
          "count": 3,
          "keywords": {
            "工程机械": 1,
            "挖掘机": 1,
            "装载机": 1
          }
        },
        {
          "name": "钢铁",
          "count": 2,
          "keywords": {
            "钢铁": 2
          }
        }
      ],
      "top_keywords": [
        [
          "市场",
          38
        ],
        [
          "增长",
          33
        ],
        [
          "投资",
          23
        ],
        [
          "亿元",
          22
        ],
        [
          "同比",
          21
        ],
        [
          "消费",
          19
        ],
        [
          "财政",
          13
        ],
        [
          "贸易",
          11
        ],
        [
          "万亿",
          9
        ],
        [
          "补贴",
          7
        ],
        [
          "预算",
          6
        ],
        [
          "万元",
          6
        ],
        [
          "百分点",
          5
        ],
        [
          "融资",
          4
        ],
        [
          "进出口",
          4
        ],
        [
          "外贸",
          4
        ],
        [
          "产值",
          4
        ],
        [
          "产能",
          3
        ],
        [
          "通胀",
          2
        ],
        [
          "税收",
          2
        ],
        [
          "零售",
          2
        ],
        [
          "订单",
          2
        ],
        [
          "千亿",
          2
        ],
        [
          "CPI",
          2
        ],
        [
          "国债",
          2
        ],
        [
          "GDP",
          2
        ],
        [
          "利润",
          1
        ],
        [
          "关税",
          1
        ],
        [
          "产量",
          1
        ],
        [
          "回升",
          1
        ]
      ]
    }
  }
}